sphinx_typo3_theme/__init__.py
sphinx_typo3_theme/breadcrumbs.html
sphinx_typo3_theme/displaysettingsui.html
sphinx_typo3_theme/domainindex.html
sphinx_typo3_theme/extensions.html
sphinx_typo3_theme/footer.html
sphinx_typo3_theme/genindex-single.html
sphinx_typo3_theme/genindex-split.html
sphinx_typo3_theme/genindex.html
sphinx_typo3_theme/layout.html
sphinx_typo3_theme/page.html
sphinx_typo3_theme/pager-hidden.html
sphinx_typo3_theme/pager.html
sphinx_typo3_theme/search.html
sphinx_typo3_theme/searchbox.html
sphinx_typo3_theme/searchresults.html
sphinx_typo3_theme/sitemap.html
sphinx_typo3_theme/theme.conf
sphinx_typo3_theme/versionhints.html
sphinx_typo3_theme/static/__init__.py
sphinx_typo3_theme/static/_version_GENERATED.py
sphinx_typo3_theme/static/_version_info_GENERATED.json
sphinx_typo3_theme/static/_version_info_GENERATED.py
sphinx_typo3_theme/static/ajax-version-hints.html
sphinx_typo3_theme/static/documentation_options.js_t
sphinx_typo3_theme/static/language_data.js_t
sphinx_typo3_theme/static/css/codeblock.css
sphinx_typo3_theme/static/css/fontawesome.css
sphinx_typo3_theme/static/css/fontawesome.css.map
sphinx_typo3_theme/static/css/theme.css
sphinx_typo3_theme/static/css/theme.css.map
sphinx_typo3_theme/static/css/webfonts.css
sphinx_typo3_theme/static/css/webfonts.css.map
sphinx_typo3_theme/static/fonts/fa-brands-400.eot
sphinx_typo3_theme/static/fonts/fa-brands-400.svg
sphinx_typo3_theme/static/fonts/fa-brands-400.ttf
sphinx_typo3_theme/static/fonts/fa-brands-400.woff
sphinx_typo3_theme/static/fonts/fa-brands-400.woff2
sphinx_typo3_theme/static/fonts/fa-regular-400.eot
sphinx_typo3_theme/static/fonts/fa-regular-400.svg
sphinx_typo3_theme/static/fonts/fa-regular-400.ttf
sphinx_typo3_theme/static/fonts/fa-regular-400.woff
sphinx_typo3_theme/static/fonts/fa-regular-400.woff2
sphinx_typo3_theme/static/fonts/fa-solid-900.eot
sphinx_typo3_theme/static/fonts/fa-solid-900.svg
sphinx_typo3_theme/static/fonts/fa-solid-900.ttf
sphinx_typo3_theme-4.9.0.dist-info/AUTHORS.rst
sphinx_typo3_theme-4.9.0.dist-info/LICENSE
sphinx_typo3_theme-4.9.0.dist-info/METADATA
sphinx_typo3_theme-4.9.0.dist-info/WHEEL
sphinx_typo3_theme-4.9.0.dist-info/entry_points.txt
sphinx_typo3_theme-4.9.0.dist-info/top_level.txt
sphinx_typo3_theme-4.9.0.dist-info/RECORD
